<?xml version="1.0" encoding="utf-8"?>
<!DOCTYPE hibernate-mapping PUBLIC "-//Hibernate/Hibernate Mapping DTD 3.0//EN"
                                   "http://hibernate.sourceforge.net/hibernate-mapping-3.0.dtd">
<!-- Mapping file autogenerated by MyEclipse Persistence Tools -->
<hibernate-mapping>
	<class catalog="app" name="bean.Collect" table="collect">
		<id name="collectId" type="java.lang.Integer">
			<column name="collectID" />
			<generator class="increment" />
		</id>
		<many-to-one class="bean.Goods" fetch="select" lazy="false" name="goods">
			<column name="goodsID" not-null="true">
				<comment>商品ID</comment>
			</column>
		</many-to-one>
		<many-to-one class="bean.Customer" fetch="select" lazy="false" name="customer">
			<column name="customerID" not-null="true">
				<comment>客户ID</comment>
			</column>
		</many-to-one>
		<property generated="never" lazy="false" name="collectDate" type="java.lang.String">
			<column length="20" name="collectDate" not-null="true">
				<comment>收藏添加日期</comment>
			</column>
		</property>
	</class>
</hibernate-mapping>
